nonebot_plugin_caiyunai/__init__.py
nonebot_plugin_caiyunai/config.py
nonebot_plugin_caiyunai/data_source.py
nonebot_plugin_caiyunai-0.2.5.dist-info/LICENSE
nonebot_plugin_caiyunai-0.2.5.dist-info/WHEEL
nonebot_plugin_caiyunai-0.2.5.dist-info/METADATA
nonebot_plugin_caiyunai-0.2.5.dist-info/RECORD
