Metadata-Version: 2.1
Name: nonebot-plugin-caiyunai
Version: 0.2.5
Summary: 适用于 Nonebot2 的彩云小梦AI续写插件
Home-page: https://github.com/noneplugin/nonebot-plugin-caiyunai
License: MIT
Author: meetwq
Author-email: meetwq@gmail.com
Requires-Python: >=3.8,<4.0
Classifier: License :: OSI Approved :: MIT License
Classifier: Programming Language :: Python :: 3
Classifier: Programming Language :: Python :: 3.10
Classifier: Programming Language :: Python :: 3.8
Classifier: Programming Language :: Python :: 3.9
Requires-Dist: httpx (>=0.19.0)
Requires-Dist: nonebot-adapter-onebot (>=2.0.0-beta.1,<3.0.0)
Requires-Dist: nonebot-plugin-imageutils (>=0.1.6,<0.2.0)
Requires-Dist: nonebot2 (>=2.0.0-beta.4,<3.0.0)
Project-URL: Repository, https://github.com/noneplugin/nonebot-plugin-caiyunai
